classification_model/VERSION
classification_model/VERSION.rtf
classification_model/__init__.py
classification_model/config.yml
classification_model/pipeline.py
classification_model/predict.py
classification_model/train_model.py
classification_model/config/__init__.py
classification_model/config/config.py
classification_model/datasets/__init__.py
classification_model/datasets/test.csv
classification_model/datasets/train.csv
classification_model/processing/__init__.py
classification_model/processing/custom_preprocess.py
classification_model/processing/data_manager.py
classification_model/processing/validation.py
classification_model/trained_models/__init__.py
classification_model/trained_models/regression_model_output_v0.0.1.pkl
titanic_classification_model_CN-0.0.1.dist-info/METADATA
titanic_classification_model_CN-0.0.1.dist-info/WHEEL
titanic_classification_model_CN-0.0.1.dist-info/top_level.txt
titanic_classification_model_CN-0.0.1.dist-info/RECORD
