Metadata-Version: 2.1
Name: titanic-classification-model-CN
Version: 0.0.1
Summary: Titanic classification model that I built while learning ML deployment.
Home-page: https://github.com/cnzdgr
Author: CN
Author-email: cnzdgr@gmail.com
License: BSD-3
Classifier: License :: OSI Approved :: MIT License
Classifier: Programming Language :: Python
Classifier: Programming Language :: Python :: 3
Classifier: Programming Language :: Python :: 3.7
Classifier: Programming Language :: Python :: 3.8
Classifier: Programming Language :: Python :: 3.9
Classifier: Programming Language :: Python :: 3.10
Classifier: Programming Language :: Python :: 3.11
Classifier: Programming Language :: Python :: Implementation :: CPython
Classifier: Programming Language :: Python :: Implementation :: PyPy
Requires-Python: >=3.7.0
Requires-Dist: numpy <2.0.0,>=1.20.0
Requires-Dist: pandas <2.0.0,>=1.2.5
Requires-Dist: pydantic <2.0.0,>=1.5.0
Requires-Dist: scikit-learn <2.0.0,>=1.2.1
Requires-Dist: strictyaml <2.0.0,>=1.5.0
Requires-Dist: ruamel.yaml <1.0.0,>=0.15.0
Requires-Dist: feature-engine <1.6.0,>=1.2.1
Requires-Dist: joblib <2.0.0,>=1.1.0
